langchain_iris/__init__.py
langchain_iris/vectorstores.py
langchain_iris-0.2.2.dist-info/licenses/LICENSE
langchain_iris-0.2.2.dist-info/METADATA
langchain_iris-0.2.2.dist-info/WHEEL
langchain_iris-0.2.2.dist-info/top_level.txt
langchain_iris-0.2.2.dist-info/RECORD
