Metadata-Version: 2.4
Name: langchain-iris
Version: 0.2.2
Summary: The InterSystems IRIS adoption for Langchain
Home-page: https://github.com/caretdev/langchain-iris
Project-URL: Source, https://github.com/caretdev/langchain-iris
Project-URL: Tracker, https://github.com/caretdev/langchain-iris/issues
Keywords: "InterSystems IRIS"
Classifier: Development Status :: 3 - Alpha
Classifier: Intended Audience :: Developers
Classifier: Programming Language :: Python
Classifier: Programming Language :: Python :: 3
Classifier: Programming Language :: Python :: 3.9
Classifier: Programming Language :: Python :: 3.10
Classifier: Programming Language :: Python :: 3.11
Classifier: Topic :: Database
Classifier: Topic :: Database :: Front-Ends
Classifier: Topic :: Software Development
Classifier: Topic :: Software Development :: Libraries :: Python Modules
Classifier: Operating System :: OS Independent
Requires-Python: >3.8
License-File: LICENSE
Requires-Dist: langchain
Requires-Dist: langchain-community
Requires-Dist: sqlalchemy-iris>=0.18.0
Dynamic: license-file
Dynamic: requires-dist
Dynamic: requires-python
